MANIFEST.in
README.rst
setup.cfg
setup.py
tests/__init__.py
tests/app_test.py
tests/excaliburgapfillvdsgenerator_test.py
tests/gapfillvdsgenerator_test.py
tests/interleavevdsgenerator_test.py
tests/reshapevdsgenerator_test.py
tests/subframevdsgenerator_test.py
tests/system_test.py
tests/vdsgenerator_test.py
vdsgen/__init__.py
vdsgen/app.py
vdsgen/excaliburgapfillvdsgenerator.py
vdsgen/gapfillvdsgenerator.py
vdsgen/interleavevdsgenerator.py
vdsgen/rawsourcegenerator.py
vdsgen/reshapevdsgenerator.py
vdsgen/subframevdsgenerator.py
vdsgen/vds.py
vdsgen/vdsgenerator.py
vdsgen.egg-info/PKG-INFO
vdsgen.egg-info/SOURCES.txt
vdsgen.egg-info/dependency_links.txt
vdsgen.egg-info/entry_points.txt
vdsgen.egg-info/not-zip-safe
vdsgen.egg-info/requires.txt
vdsgen.egg-info/top_level.txt