Metadata-Version: 1.1
Name: vdsgen
Version: 0.5.2
Summary: Creates virtual dataset HDF5 files
Home-page: https://github.com/dls-controls/vds-gen
Author: Gary Yendell
Author-email: gary.yendell@diamond.ac.uk
License: APACHE
Platform: UNKNOWN
Classifier: Development Status :: 3 - Alpha
Classifier: Intended Audience :: Developers
Classifier: Natural Language :: English
Classifier: Operating System :: POSIX :: Linux
Classifier: Programming Language :: Python :: 2.7
